glvrd/__init__.py
glvrd/client.py
glvrd/py.typed
glvrd-0.0.5.dist-info/LICENSE
glvrd-0.0.5.dist-info/METADATA
glvrd-0.0.5.dist-info/WHEEL
glvrd-0.0.5.dist-info/top_level.txt
glvrd-0.0.5.dist-info/RECORD
